bibbliothon/__init__.py
bibbliothon/authorization.py
bibbliothon/discovery.py
bibbliothon/enrichment.py
bibbliothon/helpers.py
bibbliothon/urls.py
bibbliothon-1.2.0.dist-info/DESCRIPTION.rst
bibbliothon-1.2.0.dist-info/METADATA
bibbliothon-1.2.0.dist-info/RECORD
bibbliothon-1.2.0.dist-info/WHEEL
bibbliothon-1.2.0.dist-info/metadata.json
bibbliothon-1.2.0.dist-info/top_level.txt
