Metadata-Version: 2.0
Name: bibbliothon
Version: 1.2.0
Summary: Python wrapper for Bibblio API.
Home-page: https://github.com/proversity-org/bibblio-api-python
Author: José Antonio González
Author-email: antonio@proversity.org
License: MIT License
Platform: UNKNOWN
Classifier: Development Status :: 5 - Production/Stable
Classifier: Intended Audience :: Developers
Classifier: Natural Language :: English
Classifier: License :: OSI Approved :: MIT License
Classifier: Programming Language :: Python
Requires-Dist: requests
